yaml_oop/__init__.py
yaml_oop/core/__init__.py
yaml_oop/core/custom_errors.py
yaml_oop/core/declarations.py
yaml_oop/core/parser/__init__.py
yaml_oop/core/parser/config_parser.py
yaml_oop/core/parser/context.py
yaml_oop/core/parser/inherit_parser.py
yaml_oop/core/parser/next_parser.py
yaml_oop/core/parser/parse_functions.py
yaml_oop/core/parser/variable_parser.py
yaml_oop-0.0.13.dist-info/METADATA
yaml_oop-0.0.13.dist-info/WHEEL
yaml_oop-0.0.13.dist-info/licenses/LICENSE.md
yaml_oop-0.0.13.dist-info/RECORD
