Metadata-Version: 2.4
Name: yaml_oop
Version: 0.0.13
Summary: A Python library that enables features such as inheritance, variables, and instantiation in YAML files.
Project-URL: Homepage, https://github.com/eshen2210/yaml_oop
Project-URL: Issues, https://github.com/eshen2210/yaml_oop/issues
Author-email: Edwin Shen <eshen2210@gmail.com>
License-Expression: MIT
License-File: LICENSE.md
Classifier: Operating System :: OS Independent
Classifier: Programming Language :: Python :: 3
Requires-Python: >=3.12
